client/ForesightDataPortal.py
client/__init__.py
client/foresight_request_helper.py
client/data_object/DataObject.py
client/data_object/Dataset.py
client/data_object/LazyUrlDataObject.py
client/data_object/__init__.py
fsai/__init__.py
fsai/services/DatasetService.py
fsai/services/__init__.py
fsai/services/foresight_request_helper.py
fsai/services/data_object/DataGetter.py
fsai/services/data_object/Dataset.py
fsai/services/data_object/DynamicObjectData.py
fsai/services/data_object/LazyUrlDataGetter.py
fsai/services/data_object/Semantic2DData.py
fsai/services/data_object/__init__.py
fsai_data_sdk/ForesightDataPortal.py
fsai_data_sdk/__init__.py
fsai_data_sdk/foresight_request_helper.py
fsai_data_sdk/data_object/DataGetter.py
fsai_data_sdk/data_object/DataObject.py
fsai_data_sdk/data_object/Dataset.py
fsai_data_sdk/data_object/LazyUrlDataGetter.py
fsai_data_sdk/data_object/LazyUrlDataObject.py
fsai_data_sdk/data_object/__init__.py
tests/__init__.py
tests/test_data_parser.py
tests/test_get_data.py
fsai_data_sdk-1.0.4.dist-info/METADATA
fsai_data_sdk-1.0.4.dist-info/WHEEL
fsai_data_sdk-1.0.4.dist-info/top_level.txt
fsai_data_sdk-1.0.4.dist-info/RECORD
