Metadata-Version: 2.1
Name: fsai-data-sdk
Version: 1.0.4
Summary: The official Python fsai_data_sdk library for accessing Foresight Data Portal
Home-page: https://github.com/ForesightAI/fsai_data_sdk_python
License: UNKNOWN
Keywords: foresight,foresightai,foresightai-ai
Platform: UNKNOWN
Classifier: Programming Language :: Python :: 2.7
Classifier: License :: OSI Approved :: MIT License
Classifier: Intended Audience :: Developers
Classifier: Topic :: Software Development :: Libraries
